byzfl/__init__.py
byzfl/aggregators/__init__.py
byzfl/aggregators/aggregators.py
byzfl/aggregators/preaggregators.py
byzfl/attacks/__init__.py
byzfl/attacks/attacks.py
byzfl/benchmark/__init__.py
byzfl/benchmark/benchmark.py
byzfl/benchmark/evaluate_results.py
byzfl/benchmark/managers.py
byzfl/benchmark/train.py
byzfl/fed_framework/__init__.py
byzfl/fed_framework/byzantine_client.py
byzfl/fed_framework/client.py
byzfl/fed_framework/data_distributor.py
byzfl/fed_framework/model_base_interface.py
byzfl/fed_framework/models.py
byzfl/fed_framework/robust_aggregator.py
byzfl/fed_framework/server.py
byzfl/utils/__init__.py
byzfl/utils/conversion.py
byzfl/utils/misc.py
byzfl/utils/torch_tools.py
byzfl-0.0.10.dist-info/LICENSE.txt
byzfl-0.0.10.dist-info/METADATA
byzfl-0.0.10.dist-info/WHEEL
byzfl-0.0.10.dist-info/top_level.txt
byzfl-0.0.10.dist-info/RECORD
