Metadata-Version: 2.1
Name: byzfl
Version: 0.0.10
Summary: ByzFL Library
Home-page: https://github.com/LPD-EPFL/byzfl
Author: Geovani Rizk, John Stephan, Marc Gonzalez
Author-email: geovani.rizk@epfl.ch
License-File: LICENSE.txt
Requires-Dist: torch >=2.2.0
Requires-Dist: torchvision >=0.17.0
Requires-Dist: numpy >=1.26.4
Requires-Dist: matplotlib >=3.8.3
Requires-Dist: scipy >=1.12.0
Requires-Dist: seaborn >=0.13.2
